nochi/__init__.py
nochi/calculatorTkinter.py
nochi/decimalBinaryHexadecimalConvertions.py
nochi/login.py
nochi/searchSortAlgorithms.py
nochi-0.0.3.dist-info/METADATA
nochi-0.0.3.dist-info/RECORD
nochi-0.0.3.dist-info/WHEEL
nochi-0.0.3.dist-info/top_level.txt
