Metadata-Version: 2.1
Name: nochi
Version: 0.0.3
Summary: Programmes created by me
Home-page: https://github.com/NochiZajac/programmes
Author: Nochi Zajac
Author-email: nochizajac@gmail.com
License: UNKNOWN
Platform: UNKNOWN
Classifier: Programming Language :: Python :: 3
Classifier: License :: OSI Approved :: MIT License
Classifier: Operating System :: OS Independent
